panparsex/__init__.py
panparsex/ai_processor.py
panparsex/cli.py
panparsex/core.py
panparsex/types.py
panparsex/parsers/__init__.py
panparsex/parsers/csv.py
panparsex/parsers/docx.py
panparsex/parsers/excel.py
panparsex/parsers/html.py
panparsex/parsers/json_.py
panparsex/parsers/markdown.py
panparsex/parsers/pdf.py
panparsex/parsers/pptx.py
panparsex/parsers/rtf.py
panparsex/parsers/text.py
panparsex/parsers/web.py
panparsex/parsers/web_selenium.py
panparsex/parsers/xml.py
panparsex/parsers/yaml_.py
panparsex-0.2.2.dist-info/METADATA
panparsex-0.2.2.dist-info/WHEEL
panparsex-0.2.2.dist-info/entry_points.txt
panparsex-0.2.2.dist-info/RECORD
