Metadata-Version: 2.4
Name: panparsex
Version: 0.2.2
Summary: Universal, extensible parser for many file types and websites with a clean plugin architecture.
Project-URL: Homepage, https://github.com/dhruvildarji/panparser
Project-URL: Repository, https://github.com/dhruvildarji/panparser
Project-URL: Issues, https://github.com/dhruvildarji/panparser/issues
Project-URL: Documentation, https://github.com/dhruvildarji/panparser#readme
Author-email: Dhruvil Darji <dhruvil.darji@gmail.com>
License: Apache-2.0
Keywords: crawler,etl,html,ingestion,json,parser,pdf,scraper,text,unstructured,xml,yaml
Requires-Python: >=3.9
Requires-Dist: beautifulsoup4>=4.12
Requires-Dist: chardet>=5.0.0
Requires-Dist: html5lib>=1.1
Requires-Dist: lxml>=5.0
Requires-Dist: markdown-it-py>=3.0
Requires-Dist: openai>=1.0.0
Requires-Dist: openpyxl>=3.1.0
Requires-Dist: pdfminer-six>=20221105
Requires-Dist: pydantic>=2.5
Requires-Dist: pypdf>=3.0
Requires-Dist: python-docx>=0.8.11
Requires-Dist: python-magic>=0.4.27
Requires-Dist: python-pptx>=0.6.21
Requires-Dist: pyyaml>=6.0
Requires-Dist: requests>=2.31
Requires-Dist: tqdm>=4.66
Provides-Extra: dev
Requires-Dist: bandit>=1.7; extra == 'dev'
Requires-Dist: black>=23.0; extra == 'dev'
Requires-Dist: flake8>=6.0; extra == 'dev'
Requires-Dist: mypy>=1.0; extra == 'dev'
Requires-Dist: pre-commit>=3.0; extra == 'dev'
Requires-Dist: pytest-cov>=4.0; extra == 'dev'
Requires-Dist: pytest>=7.0; extra == 'dev'
Requires-Dist: safety>=2.0; extra == 'dev'
Provides-Extra: selenium
Requires-Dist: selenium>=4.0.0; extra == 'selenium'
Requires-Dist: webdriver-manager>=3.8.0; extra == 'selenium'
